vnpyrs-0.2.1.dist-info/METADATA
vnpyrs-0.2.1.dist-info/WHEEL
vnpyrs-0.2.1.dist-info/licenses/LICENSE
vnpyrs/base_widget.py
vnpyrs/engine.py
vnpyrs/event_engine.py
vnpyrs/optimize.py
vnpyrs/utility.py
vnpyrs/widget.py
vnpyrs/__init__.py
vnpyrs/vnpyrs.pyd
vnpyrs-0.2.1.dist-info/RECORD
