Metadata-Version: 2.4
Name: vnpyrs
Version: 0.2.1
Classifier: Development Status :: 4 - Beta
Classifier: Environment :: Console
Classifier: Intended Audience :: Science/Research
Classifier: License :: OSI Approved :: MIT License
Classifier: Operating System :: OS Independent
Classifier: Programming Language :: Rust
Classifier: Programming Language :: Python :: 3.7
Classifier: Programming Language :: Python :: 3.8
Classifier: Programming Language :: Python :: 3.9
Classifier: Programming Language :: Python :: 3.10
Classifier: Programming Language :: Python :: 3.11
Classifier: Programming Language :: Python :: 3.12
Classifier: Programming Language :: Python :: 3.13
Classifier: Programming Language :: Python :: Implementation :: CPython
Classifier: Topic :: Office/Business :: Financial :: Investment
Classifier: Natural Language :: Chinese (Simplified)
Requires-Dist: tzlocal
Requires-Dist: pyside6
Requires-Dist: pyqtgraph
Requires-Dist: numpy
Requires-Dist: pandas
Requires-Dist: ta-lib
Requires-Dist: deap
Requires-Dist: plotly
Requires-Dist: pytz
Requires-Dist: tqdm
License-File: LICENSE
Summary: vnpy backtest module written in Rust and Python
Keywords: quant,quantitative,investment,trading
Home-Page: https://github.com/vnpyrs/vnpyrs
Author: Liehan Wu <vnpyrs@hotmail.com>
Author-email: Liehan Wu <vnpyrs@hotmail.com>
License: MIT
Requires-Python: >=3.7
Project-URL: Homepage, https://vnpyrs.com/
Project-URL: Documentation, https://vnpyrs.com/docs/intro/
Project-URL: Repository, https://github.com/vnpyrs/vnpyrs
Project-URL: Changelog, https://github.com/vnpyrs/vnpyrs
